<?xml version="1.0"?>
<!DOCTYPE hibernate-mapping PUBLIC "-//Hibernate/Hibernate Mapping DTD 2.0//EN"
"http://hibernate.sourceforge.net/hibernate-mapping-2.0.dtd">
<!-- 
    Mapping file autogenerated by MyEclipse - Hibernate Tools
-->
<hibernate-mapping>
    <class name="server.essp.projectpre.db.PPLog" table="PP_LOG" >
        <id name="rid" type="long">
            <column name="RID" />
            <generator class="assigned"></generator>
        </id>
        <property name="acntId" type="string">
            <column name="ACNT_ID" length="50" not-null="true" />
        </property>
        <property name="dataType" type="string">
            <column name="DATA_TYPE" length="20" />
        </property>
        <property name="applicationType" type="string">
            <column name="APPLICATION_TYPE" length="50" />
        </property>
        <property name="operation" type="string">
            <column name="OPERATION" length="10" />
        </property>
        <property name="operationDate" type="timestamp">
            <column name="OPERATION_DATE" length="7" />
        </property>
        <property name="operator" type="string">
            <column name="OPERATOR" length="50" />
        </property>
        <property name="mailReceiver" type="string">
            <column name="MAIL_RECEIVER" length="1000" />
        </property>
    </class>
</hibernate-mapping>
